openide/__init__.py
openide/integration.py
openide/py.typed
openide/actions/__init__.py
openide/lookups/__init__.py
openide/lookups/egg_info.py
openide/lookups/global_context.py
openide/lookups/main_lookup.py
openide/lookups/services.py
openide/startup/__init__.py
openide/startup/main.py
openide/utils/__init__.py
openide/utils/classes.py
openide/utils/datastructures.py
openide/windows/__init__.py
openide/windows/context_tracker.py
openide/windows/main_window.py
openide/windows/top_component.py
openide/windows/window_manager.py
openide-0.0.1.dist-info/LICENSE
openide-0.0.1.dist-info/METADATA
openide-0.0.1.dist-info/WHEEL
openide-0.0.1.dist-info/entry_points.txt
openide-0.0.1.dist-info/openide.yaml
openide-0.0.1.dist-info/top_level.txt
openide-0.0.1.dist-info/RECORD
