Metadata-Version: 2.1
Name: openide
Version: 0.0.1
Summary: Python implementation of openide/Netbeans Platform concepts
Home-page: https://github.com/AxelVoitier/openide
Author: Axel Voitier
Author-email: axel.voitier@gmail.com
License: MPLv2
Platform: UNKNOWN
Classifier: Development Status :: 3 - Alpha
Classifier: Intended Audience :: Developers
Classifier: License :: OSI Approved :: Mozilla Public License 2.0 (MPL 2.0)
Classifier: Programming Language :: Python :: 3
Classifier: Topic :: Desktop Environment
Classifier: Topic :: Software Development :: User Interfaces
Classifier: Topic :: Text Editors :: Integrated Development Environments (IDE)
Requires-Python: ~=3.7
Requires-Dist: PySide2
Requires-Dist: PyYaml
Requires-Dist: lookups
Requires-Dist: observable
Requires-Dist: qtpy
Provides-Extra: dev
Requires-Dist: check-manifest ; extra == 'dev'
Requires-Dist: flake8 ; extra == 'dev'
Requires-Dist: mypy ; extra == 'dev'
Requires-Dist: pytest ; extra == 'dev'
Requires-Dist: pytest-cov ; extra == 'dev'
Requires-Dist: pytest-html ; extra == 'dev'
